psis/__init__.py
psis/indices.py
tests/__init__.py
tests/sample_data.py
tests/test_psis.py
psis-0.3.0.dist-info/LICENSE
psis-0.3.0.dist-info/METADATA
psis-0.3.0.dist-info/WHEEL
psis-0.3.0.dist-info/top_level.txt
psis-0.3.0.dist-info/RECORD
